plone.formwidget.recurrence-3.0.6-py3.13-nspkg.pth
plone/formwidget/recurrence/__init__.py
plone/formwidget/recurrence/configure.zcml
plone/formwidget/recurrence/browser/__init__.py
plone/formwidget/recurrence/browser/configure.zcml
plone/formwidget/recurrence/browser/i18n.py
plone/formwidget/recurrence/browser/json_recurrence.py
plone/formwidget/recurrence/profiles/default/metadata.xml
plone/formwidget/recurrence/tests/__init__.py
plone/formwidget/recurrence/tests/base.py
plone/formwidget/recurrence/tests/test_z3cwidget.py
plone/formwidget/recurrence/z3cform/__init__.py
plone/formwidget/recurrence/z3cform/configure.zcml
plone/formwidget/recurrence/z3cform/field.py
plone/formwidget/recurrence/z3cform/interfaces.py
plone/formwidget/recurrence/z3cform/recurrence_hidden.pt
plone/formwidget/recurrence/z3cform/recurrence_input.pt
plone/formwidget/recurrence/z3cform/widget.py
plone_formwidget_recurrence-3.0.6.dist-info/METADATA
plone_formwidget_recurrence-3.0.6.dist-info/WHEEL
plone_formwidget_recurrence-3.0.6.dist-info/entry_points.txt
plone_formwidget_recurrence-3.0.6.dist-info/namespace_packages.txt
plone_formwidget_recurrence-3.0.6.dist-info/top_level.txt
plone_formwidget_recurrence-3.0.6.dist-info/RECORD
