Metadata-Version: 2.4
Name: plone.formwidget.recurrence
Version: 3.0.6
Summary: Recurrence widget for Plone
Home-page: https://github.com/plone/plone.formwidget.recurrence
Author: Plone Foundation
Author-email: plone-developers@lists.sourceforge.net
License: GPL
Keywords: Plone Event Recurrence Date Time Widget z3c.form
Classifier: Development Status :: 5 - Production/Stable
Classifier: Framework :: Plone
Classifier: Framework :: Plone :: 6.0
Classifier: License :: OSI Approved :: GNU General Public License (GPL)
Classifier: Programming Language :: Python
Classifier: Programming Language :: Python :: 3.8
Classifier: Programming Language :: Python :: 3.9
Classifier: Programming Language :: Python :: 3.10
Classifier: Programming Language :: Python :: 3.11
Requires-Python: >=3.8
Requires-Dist: setuptools
Requires-Dist: plone.base
Requires-Dist: Products.GenericSetup
Requires-Dist: python-dateutil
Requires-Dist: Zope
Provides-Extra: z3cform
Requires-Dist: z3c.form; extra == "z3cform"
Provides-Extra: test
Requires-Dist: plone.app.testing; extra == "test"
Requires-Dist: plone.app.z3cform; extra == "test"
Dynamic: author
Dynamic: author-email
Dynamic: classifier
Dynamic: description
Dynamic: home-page
Dynamic: keywords
Dynamic: license
Dynamic: provides-extra
Dynamic: requires-dist
Dynamic: requires-python
Dynamic: summary
